{
  "id": "https://sophiedixon.github.io/3d-portfolio/collection/human_skull/index.json",
  "type": "Manifest",
  "items": [
    {
      "id": "https://sophiedixon.github.io/3d-portfolio/collection/human_skull/index.json/canvas/0",
      "type": "Canvas",
      "items": [
        {
          "id": "https://sophiedixon.github.io/3d-portfolio/collection/human_skull/index.json/canvas/0/annotationpage/0",
          "type": "AnnotationPage",
          "items": [
            {
              "id": "https://sophiedixon.github.io/3d-portfolio/collection/human_skull/index.json/canvas/0/annotation/0",
              "type": "Annotation",
              "motivation": "painting",
              "body": {
                "id": "https://sophiedixon.github.io/3d-portfolio/collection/human_skull/_human_skull/skull_diffuse.png",
                "type": "Image",
                "format": "image/png",
                "label": {
                  "@none": [
                    "_human_skull"
                  ]
                }
              },
              "target": "https://sophiedixon.github.io/3d-portfolio/collection/human_skull/index.json/canvas/0"
            },
            {
              "id": "https://sophiedixon.github.io/3d-portfolio/collection/human_skull/index.json/canvas/0/annotation/1",
              "type": "Annotation",
              "motivation": "painting",
              "body": {
                "id": "https://sophiedixon.github.io/3d-portfolio/collection/human_skull/_human_skull/skull_normal.png",
                "type": "Image",
                "format": "image/png",
                "label": {
                  "@none": [
                    "_human_skull"
                  ]
                }
              },
              "target": "https://sophiedixon.github.io/3d-portfolio/collection/human_skull/index.json/canvas/0"
            },
            {
              "id": "https://sophiedixon.github.io/3d-portfolio/collection/human_skull/index.json/canvas/0/annotation/2",
              "type": "Annotation",
              "motivation": "painting",
              "body": {
                "id": "https://sophiedixon.github.io/3d-portfolio/collection/human_skull/_human_skull/skull.obj",
                "type": "PhysicalObject",
                "format": "text/plain",
                "label": {
                  "@none": [
                    "_human_skull"
                  ]
                }
              },
              "target": "https://sophiedixon.github.io/3d-portfolio/collection/human_skull/index.json/canvas/0"
            }
          ]
        }
      ],
      "label": {
        "@none": [
          "_human_skull"
        ]
      },
      "thumbnail": [
        {
          "id": "https://sophiedixon.github.io/3d-portfolio/collection/human_skull/_human_skull/thumb.png",
          "type": "Image"
        }
      ]
    }
  ],
  "label": {
    "@none": [
      "Human Skull"
    ]
  },
  "metadata": [
    {
      "label": {
        "@none": [
          "Made with"
        ]
      },
      "value": {
        "@none": [
          "Agisoft PhotoScan & Blender"
        ]
      }
    }
  ],
  "attribution": "Nelis Antiques, Amsterdam. www.nelisantiques.com",
  "description": "Paediatric skull with developing dentition",
  "thumbnail": [
    {
      "id": "https://sophiedixon.github.io/3d-portfolio/collection/human_skull/thumb.jpg",
      "type": "Image"
    }
  ]
}